pathtree/__init__.py
pathtree/__main__.py
pathtree/pathtree.py
pathtree-0.1.3.dist-info/METADATA
pathtree-0.1.3.dist-info/RECORD
pathtree-0.1.3.dist-info/WHEEL
pathtree-0.1.3.dist-info/top_level.txt
